LICENSE.txt
MANIFEST.in
setup.cfg
setup.py
tracermppt.py
tracermppt.egg-info/PKG-INFO
tracermppt.egg-info/SOURCES.txt
tracermppt.egg-info/dependency_links.txt
tracermppt.egg-info/requires.txt
tracermppt.egg-info/top_level.txt