Metadata-Version: 1.1
Name: tracermppt
Version: 0.2
Summary: Interface for controlling and interrogating the Tracer-2210RN and similar charge cotnrollers via the remote monitoring port
Home-page: https://github.com/bmayton/tracermppt
Author: Brian Mayton
Author-email: bmayton@media.mit.edu
License: MIT
Download-URL: https://github.com/bmayton/tracermppt/tarball/0.2
Platform: UNKNOWN
